{"Dot":"[{\"Id\":0,\"X\":489,\"Y\":108,\"Index\":1,\"Text\":\"A\",\"ShapeType\":1,\"Color\":\"Black\",\"Width\":1,\"LockLine\":{\"Id\":-1},\"LockCirle\":{\"Id\":-1},\"LockLineRation\":0,\"Size\":6,\"LockCircleAngle\":0,\"Font\":\"微软雅黑,11pt,style=Bold\",\"Lines\":[{\"Id\":3},{\"Id\":5}]},{\"Id\":2,\"X\":1153.485,\"Y\":398.0891,\"Index\":0,\"Text\":\"C\",\"ShapeType\":1,\"Color\":\"Black\",\"Width\":1,\"LockLine\":{\"Id\":-1},\"LockCirle\":{\"Id\":7},\"LockLineRation\":0,\"Size\":6,\"LockCircleAngle\":2.567794,\"Font\":\"微软雅黑,11pt,style=Bold\",\"Lines\":[{\"Id\":4},{\"Id\":5}]},{\"Id\":6,\"X\":1248,\"Y\":337,\"Index\":0,\"Text\":\"D\",\"ShapeType\":1,\"Color\":\"Red\",\"Width\":1,\"LockLine\":{\"Id\":-1},\"LockCirle\":{\"Id\":-1},\"LockLineRation\":0,\"Size\":6,\"LockCircleAngle\":0,\"Font\":\"微软雅黑,11pt,style=Bold\",\"Circles\":[{\"Id\":7},{\"Id\":7},{\"Id\":7}]},{\"Id\":8,\"X\":321,\"Y\":500,\"Index\":0,\"Text\":\"E\",\"ShapeType\":1,\"Color\":\"Black\",\"Width\":1,\"LockLine\":{\"Id\":-1},\"LockCirle\":{\"Id\":-1},\"LockLineRation\":0,\"Size\":6,\"LockCircleAngle\":0,\"Font\":\"微软雅黑,11pt,style=Bold\",\"Lines\":[{\"Id\":10},{\"Id\":3},{\"Id\":4},{\"Id\":16},{\"Id\":17}]},{\"Id\":9,\"X\":868.6097,\"Y\":273.6707,\"Index\":2,\"Text\":\"F\",\"ShapeType\":1,\"Color\":\"Black\",\"Width\":1,\"LockLine\":{\"Id\":5},\"LockCirle\":{\"Id\":-1},\"LockLineRation\":0.4287447,\"Size\":6,\"LockCircleAngle\":0,\"Font\":\"微软雅黑,11pt,style=Bold\",\"Lines\":[{\"Id\":10}]},{\"Id\":12,\"X\":90,\"Y\":110,\"Index\":0,\"Text\":\"A\",\"ShapeType\":1,\"Color\":\"Black\",\"Width\":1,\"LockLine\":{\"Id\":-1},\"LockCirle\":{\"Id\":-1},\"LockLineRation\":0,\"Size\":6,\"LockCircleAngle\":0,\"Font\":\"微软雅黑,11pt,style=Bold\",\"Lines\":[{\"Id\":15},{\"Id\":17}]},{\"Id\":13,\"X\":57,\"Y\":595,\"Index\":0,\"Text\":\"B\",\"ShapeType\":1,\"Color\":\"Black\",\"Width\":1,\"LockLine\":{\"Id\":-1},\"LockCirle\":{\"Id\":-1},\"LockLineRation\":0,\"Size\":6,\"LockCircleAngle\":0,\"Font\":\"微软雅黑,11pt,style=Bold\",\"Lines\":[{\"Id\":15},{\"Id\":16}]}]","Line":"[{\"Id\":3,\"From\":{\"Id\":0},\"To\":{\"Id\":8},\"Index\":0,\"Text\":\"\",\"ShapeType\":2,\"Color\":\"DarkBlue\",\"Width\":2,},{\"Id\":4,\"From\":{\"Id\":8},\"To\":{\"Id\":2},\"Index\":0,\"Text\":\"\",\"ShapeType\":2,\"Color\":\"DarkBlue\",\"Width\":2,},{\"Id\":5,\"From\":{\"Id\":2},\"To\":{\"Id\":0},\"Index\":0,\"Text\":\"\",\"ShapeType\":2,\"Color\":\"DarkBlue\",\"Width\":2,},{\"Id\":10,\"From\":{\"Id\":8},\"To\":{\"Id\":9},\"Index\":0,\"Text\":\"\",\"ShapeType\":2,\"Color\":\"DarkBlue\",\"Width\":2,},{\"Id\":15,\"From\":{\"Id\":12},\"To\":{\"Id\":13},\"Index\":0,\"Text\":\"\",\"ShapeType\":2,\"Color\":\"DarkBlue\",\"Width\":2,},{\"Id\":16,\"From\":{\"Id\":13},\"To\":{\"Id\":8},\"Index\":0,\"Text\":\"\",\"ShapeType\":2,\"Color\":\"DarkBlue\",\"Width\":2,},{\"Id\":17,\"From\":{\"Id\":8},\"To\":{\"Id\":12},\"Index\":0,\"Text\":\"\",\"ShapeType\":2,\"Color\":\"DarkBlue\",\"Width\":2,}]","FillArea":"[{\"Id\":11,\"Index\":0,\"Text\":\"A\",\"ShapeType\":4,\"Color\":\"Orange\",\"Width\":1,\"Dots\":[{\"Id\":0},{\"Id\":8},{\"Id\":9}]}]","Circle":"[{\"Id\":7,\"Center\":{\"Id\":6},\"Index\":0,\"Text\":\"A\",\"ShapeType\":5,\"Color\":\"DarkBlue\",\"Width\":2,\"Diam\":225.0778}]"}